LICENSE
MANIFEST.in
README.md
setup.py
djsearch/__init__.py
djsearch/admin.py
djsearch/apps.py
djsearch/models.py
djsearch/tests.py
djsearch/urls.py
djsearch/utils.py
djsearch/views.py
djsearch.egg-info/PKG-INFO
djsearch.egg-info/SOURCES.txt
djsearch.egg-info/dependency_links.txt
djsearch.egg-info/top_level.txt
djsearch/migrations/__init__.py
djsearch/templates/djsearch/results.html